pygmo_plugins_nonfree.libs/libblas-fe34f726.so.3.8.0
pygmo_plugins_nonfree.libs/libipopt-8adcd530.so.3.14.10
pygmo_plugins_nonfree.libs/libgfortran-ce9df58f.so.5.0.0
pygmo_plugins_nonfree.libs/libboost_serialization-1464d039.so.1.80.0
pygmo_plugins_nonfree.libs/libquadmath-aa18d9dd.so.0.0.0
pygmo_plugins_nonfree.libs/libboost_filesystem-39173a3b.so.1.80.0
pygmo_plugins_nonfree.libs/libcoinmumps-077828a7.so.3.0.4
pygmo_plugins_nonfree.libs/liblapack-31d7d384.so.3.8.0
pygmo_plugins_nonfree.libs/libnlopt-ed026f9e.so.0.11.1
pygmo_plugins_nonfree.libs/libpagmo-fdf175e5.so.9.0
pygmo_plugins_nonfree.libs/libtbb-330f1dc8.so.12.7
pygmo_plugins_nonfree.libs/libpagmo_plugins_nonfree-b02a44ba.so.1.0
pygmo_plugins_nonfree.libs/libboost_atomic-a9fac401.so.1.80.0
pygmo_plugins_nonfree.libs/libboost_system-f123975b.so.1.80.0
pygmo_plugins_nonfree-0.24.dist-info/METADATA
pygmo_plugins_nonfree-0.24.dist-info/RECORD
pygmo_plugins_nonfree-0.24.dist-info/top_level.txt
pygmo_plugins_nonfree-0.24.dist-info/WHEEL
pygmo_plugins_nonfree/__init__.py
pygmo_plugins_nonfree/_version.py
pygmo_plugins_nonfree/test.py
pygmo_plugins_nonfree/core.so
